setup.py
Object_anku_2/hello.py
anku1_rce.egg-info/PKG-INFO
anku1_rce.egg-info/SOURCES.txt
anku1_rce.egg-info/dependency_links.txt
anku1_rce.egg-info/top_level.txt