Metadata-Version: 2.4
Name: anku1-rce
Version: 0.0.1
Summary: Install this module to trigger reverse shell
Author: Object_anku_2
Dynamic: author
Dynamic: summary
